rgd_client/__init__.py
rgd_client/_plugin_utils.py
rgd_client/_version.py
rgd_client/client.py
rgd_client/plugin.py
rgd_client/pytorch.py
rgd_client/session.py
rgd_client/types.py
rgd_client/utils.py
rgd_client-0.3.11.dist-info/METADATA
rgd_client-0.3.11.dist-info/WHEEL
rgd_client-0.3.11.dist-info/top_level.txt
rgd_client-0.3.11.dist-info/RECORD
