Metadata-Version: 2.1
Name: rgd-client
Version: 0.3.11
Summary: Make web requests to a Resonant GeoData instance.
Home-page: https://github.com/ResonantGeoData/ResonantGeoData
Author: Kitware, Inc.
Author-email: rgd@kitware.com
License: Apache 2.0
Platform: UNKNOWN
Classifier: Development Status :: 3 - Alpha
Classifier: License :: OSI Approved :: Apache Software License
Classifier: Programming Language :: Python :: 3
Classifier: Programming Language :: Python :: 3.8
Classifier: Programming Language :: Python
Requires-Python: >=3.8
Requires-Dist: requests
Requires-Dist: requests-toolbelt
Requires-Dist: geomet
Requires-Dist: tqdm
Requires-Dist: validators
Provides-Extra: dev
Requires-Dist: ipython ; extra == 'dev'
